README.rst
get_firefox_urls.py
setup.py
get_firefox_urls.egg-info/PKG-INFO
get_firefox_urls.egg-info/SOURCES.txt
get_firefox_urls.egg-info/dependency_links.txt
get_firefox_urls.egg-info/entry_points.txt
get_firefox_urls.egg-info/requires.txt
get_firefox_urls.egg-info/top_level.txt