Metadata-Version: 1.1
Name: get-firefox-urls
Version: 0.1.2
Summary: Utility to print the URLs currently open in Firefox.
Home-page: https://github.com/luismsgomes/get-firefox-urls
Author: Luís Gomes
Author-email: luismsgomes@gmail.com
License: MIT
Keywords: firefox util commandline
Platform: UNKNOWN
Classifier: Development Status :: 3 - Alpha
Classifier: License :: OSI Approved :: MIT License
Classifier: Programming Language :: Python :: 3.7
